<?xml version="1.0" encoding="UTF-8"?><?xml-stylesheet type='text/xsl' href='_UpgradeReport_Files/UpgradeReport.xslt'?><UpgradeLog>
<Properties><Property Name="Solution" Value="sx1231skb">
</Property><Property Name="Solution File" Value="C:\Users\Coskun ERGAN\Desktop\FTDI_SPI\SX1231-master\sx1231skb.sln">
</Property><Property Name="User Options File" Value="C:\Users\Coskun ERGAN\Desktop\FTDI_SPI\SX1231-master\sx1231skb.suo">
</Property><Property Name="Date" Value="29 Ağustos 2019 Perşembe">
</Property><Property Name="Time" Value="19:41">
</Property></Properties><Event ErrorLevel="0" Project="" Source="sx1231skb.sln" Description="File successfully backed up as C:\Users\Coskun ERGAN\Desktop\FTDI_SPI\SX1231-master\Backup\sx1231skb.sln">
</Event><Event ErrorLevel="0" Project="" Source="sx1231skb.suo" Description="File successfully backed up as C:\Users\Coskun ERGAN\Desktop\FTDI_SPI\SX1231-master\Backup\sx1231skb.suo">
</Event><Event ErrorLevel="0" Project="sx1231skb" Source="sx1231skb\sx1231skb.csproj" Description="Project file successfully backed up as C:\Users\Coskun ERGAN\Desktop\FTDI_SPI\SX1231-master\Backup\sx1231skb\sx1231skb.csproj">
</Event><Event ErrorLevel="0" Project="sx1231skb" Source="sx1231skb\AssemblyInfo.cs" Description="File successfully backed up as C:\Users\Coskun ERGAN\Desktop\FTDI_SPI\SX1231-master\Backup\sx1231skb\AssemblyInfo.cs">
</Event><Event ErrorLevel="0" Project="sx1231skb" Source="sx1231skb\MainForm.cs" Description="File successfully backed up as C:\Users\Coskun ERGAN\Desktop\FTDI_SPI\SX1231-master\Backup\sx1231skb\MainForm.cs">
</Event><Event ErrorLevel="0" Project="sx1231skb" Source="sx1231skb\AboutBox.cs" Description="File successfully backed up as C:\Users\Coskun ERGAN\Desktop\FTDI_SPI\SX1231-master\Backup\sx1231skb\AboutBox.cs">
</Event><Event ErrorLevel="0" Project="sx1231skb" Source="sx1231skb\HelpForm.cs" Description="File successfully backed up as C:\Users\Coskun ERGAN\Desktop\FTDI_SPI\SX1231-master\Backup\sx1231skb\HelpForm.cs">
</Event><Event ErrorLevel="0" Project="sx1231skb" Source="sx1231skb\Program.cs" Description="File successfully backed up as C:\Users\Coskun ERGAN\Desktop\FTDI_SPI\SX1231-master\Backup\sx1231skb\Program.cs">
</Event><Event ErrorLevel="0" Project="sx1231skb" Source="sx1231skb\Properties\Settings.cs" Description="File successfully backed up as C:\Users\Coskun ERGAN\Desktop\FTDI_SPI\SX1231-master\Backup\sx1231skb\Properties\Settings.cs">
</Event><Event ErrorLevel="0" Project="sx1231skb" Source="sx1231skb\Properties\Resources.cs" Description="File successfully backed up as C:\Users\Coskun ERGAN\Desktop\FTDI_SPI\SX1231-master\Backup\sx1231skb\Properties\Resources.cs">
</Event><Event ErrorLevel="0" Project="sx1231skb" Source="sx1231skb\Doc\Common\Battery management.html" Description="File successfully backed up as C:\Users\Coskun ERGAN\Desktop\FTDI_SPI\SX1231-master\Backup\sx1231skb\Doc\Common\Battery management.html">
</Event><Event ErrorLevel="0" Project="sx1231skb" Source="sx1231skb\Doc\Common\Bit synchronizer Data mode.html" Description="File successfully backed up as C:\Users\Coskun ERGAN\Desktop\FTDI_SPI\SX1231-master\Backup\sx1231skb\Doc\Common\Bit synchronizer Data mode.html">
</Event><Event ErrorLevel="0" Project="sx1231skb" Source="sx1231skb\Doc\Common\Device status.html" Description="File successfully backed up as C:\Users\Coskun ERGAN\Desktop\FTDI_SPI\SX1231-master\Backup\sx1231skb\Doc\Common\Device status.html">
</Event><Event ErrorLevel="0" Project="sx1231skb" Source="sx1231skb\Doc\Common\General.html" Description="File successfully backed up as C:\Users\Coskun ERGAN\Desktop\FTDI_SPI\SX1231-master\Backup\sx1231skb\Doc\Common\General.html">
</Event><Event ErrorLevel="0" Project="sx1231skb" Source="sx1231skb\Doc\Common\Listen mode.html" Description="File successfully backed up as C:\Users\Coskun ERGAN\Desktop\FTDI_SPI\SX1231-master\Backup\sx1231skb\Doc\Common\Listen mode.html">
</Event><Event ErrorLevel="0" Project="sx1231skb" Source="sx1231skb\Doc\Common\Modulation.html" Description="File successfully backed up as C:\Users\Coskun ERGAN\Desktop\FTDI_SPI\SX1231-master\Backup\sx1231skb\Doc\Common\Modulation.html">
</Event><Event ErrorLevel="0" Project="sx1231skb" Source="sx1231skb\Doc\Common\Operating mode.html" Description="File successfully backed up as C:\Users\Coskun ERGAN\Desktop\FTDI_SPI\SX1231-master\Backup\sx1231skb\Doc\Common\Operating mode.html">
</Event><Event ErrorLevel="0" Project="sx1231skb" Source="sx1231skb\Doc\Common\Oscillators.html" Description="File successfully backed up as C:\Users\Coskun ERGAN\Desktop\FTDI_SPI\SX1231-master\Backup\sx1231skb\Doc\Common\Oscillators.html">
</Event><Event ErrorLevel="0" Project="sx1231skb" Source="sx1231skb\Doc\global.css" Description="File successfully backed up as C:\Users\Coskun ERGAN\Desktop\FTDI_SPI\SX1231-master\Backup\sx1231skb\Doc\global.css">
</Event><Event ErrorLevel="0" Project="sx1231skb" Source="sx1231skb\Doc\Irq mapping\Clock out.html" Description="File successfully backed up as C:\Users\Coskun ERGAN\Desktop\FTDI_SPI\SX1231-master\Backup\sx1231skb\Doc\Irq mapping\Clock out.html">
</Event><Event ErrorLevel="0" Project="sx1231skb" Source="sx1231skb\Doc\Irq mapping\DIO mapping.html" Description="File successfully backed up as C:\Users\Coskun ERGAN\Desktop\FTDI_SPI\SX1231-master\Backup\sx1231skb\Doc\Irq mapping\DIO mapping.html">
</Event><Event ErrorLevel="0" Project="sx1231skb" Source="sx1231skb\Doc\Irq mapping\Irq flags.html" Description="File successfully backed up as C:\Users\Coskun ERGAN\Desktop\FTDI_SPI\SX1231-master\Backup\sx1231skb\Doc\Irq mapping\Irq flags.html">
</Event><Event ErrorLevel="0" Project="sx1231skb" Source="sx1231skb\Doc\overview.html" Description="File successfully backed up as C:\Users\Coskun ERGAN\Desktop\FTDI_SPI\SX1231-master\Backup\sx1231skb\Doc\overview.html">
</Event><Event ErrorLevel="0" Project="sx1231skb" Source="sx1231skb\Doc\Packet handler\Address filtering.html" Description="File successfully backed up as C:\Users\Coskun ERGAN\Desktop\FTDI_SPI\SX1231-master\Backup\sx1231skb\Doc\Packet handler\Address filtering.html">
</Event><Event ErrorLevel="0" Project="sx1231skb" Source="sx1231skb\Doc\Packet handler\Aes encryption.html" Description="File successfully backed up as C:\Users\Coskun ERGAN\Desktop\FTDI_SPI\SX1231-master\Backup\sx1231skb\Doc\Packet handler\Aes encryption.html">
</Event><Event ErrorLevel="0" Project="sx1231skb" Source="sx1231skb\Doc\Packet handler\Aes key value.html" Description="File successfully backed up as C:\Users\Coskun ERGAN\Desktop\FTDI_SPI\SX1231-master\Backup\sx1231skb\Doc\Packet handler\Aes key value.html">
</Event><Event ErrorLevel="0" Project="sx1231skb" Source="sx1231skb\Doc\Packet handler\Broadcast address.html" Description="File successfully backed up as C:\Users\Coskun ERGAN\Desktop\FTDI_SPI\SX1231-master\Backup\sx1231skb\Doc\Packet handler\Broadcast address.html">
</Event><Event ErrorLevel="0" Project="sx1231skb" Source="sx1231skb\Doc\Packet handler\Control.html" Description="File successfully backed up as C:\Users\Coskun ERGAN\Desktop\FTDI_SPI\SX1231-master\Backup\sx1231skb\Doc\Packet handler\Control.html">
</Event><Event ErrorLevel="0" Project="sx1231skb" Source="sx1231skb\Doc\Packet handler\Crc auto clear.html" Description="File successfully backed up as C:\Users\Coskun ERGAN\Desktop\FTDI_SPI\SX1231-master\Backup\sx1231skb\Doc\Packet handler\Crc auto clear.html">
</Event><Event ErrorLevel="0" Project="sx1231skb" Source="sx1231skb\Doc\Packet handler\Crc calculation.html" Description="File successfully backed up as C:\Users\Coskun ERGAN\Desktop\FTDI_SPI\SX1231-master\Backup\sx1231skb\Doc\Packet handler\Crc calculation.html">
</Event><Event ErrorLevel="0" Project="sx1231skb" Source="sx1231skb\Doc\Packet handler\Dc free.html" Description="File successfully backed up as C:\Users\Coskun ERGAN\Desktop\FTDI_SPI\SX1231-master\Backup\sx1231skb\Doc\Packet handler\Dc free.html">
</Event><Event ErrorLevel="0" Project="sx1231skb" Source="sx1231skb\Doc\Packet handler\Fifo fill condition.html" Description="File successfully backed up as C:\Users\Coskun ERGAN\Desktop\FTDI_SPI\SX1231-master\Backup\sx1231skb\Doc\Packet handler\Fifo fill condition.html">
</Event><Event ErrorLevel="0" Project="sx1231skb" Source="sx1231skb\Doc\Packet handler\Fifo threshold.html" Description="File successfully backed up as C:\Users\Coskun ERGAN\Desktop\FTDI_SPI\SX1231-master\Backup\sx1231skb\Doc\Packet handler\Fifo threshold.html">
</Event><Event ErrorLevel="0" Project="sx1231skb" Source="sx1231skb\Doc\Packet handler\Inter packet rx delay.html" Description="File successfully backed up as C:\Users\Coskun ERGAN\Desktop\FTDI_SPI\SX1231-master\Backup\sx1231skb\Doc\Packet handler\Inter packet rx delay.html">
</Event><Event ErrorLevel="0" Project="sx1231skb" Source="sx1231skb\Doc\Packet handler\Intermediate mode enter.html" Description="File successfully backed up as C:\Users\Coskun ERGAN\Desktop\FTDI_SPI\SX1231-master\Backup\sx1231skb\Doc\Packet handler\Intermediate mode enter.html">
</Event><Event ErrorLevel="0" Project="sx1231skb" Source="sx1231skb\Doc\Packet handler\Intermediate mode exit.html" Description="File successfully backed up as C:\Users\Coskun ERGAN\Desktop\FTDI_SPI\SX1231-master\Backup\sx1231skb\Doc\Packet handler\Intermediate mode exit.html">
</Event><Event ErrorLevel="0" Project="sx1231skb" Source="sx1231skb\Doc\Packet handler\Intermediate mode.html" Description="File successfully backed up as C:\Users\Coskun ERGAN\Desktop\FTDI_SPI\SX1231-master\Backup\sx1231skb\Doc\Packet handler\Intermediate mode.html">
</Event><Event ErrorLevel="0" Project="sx1231skb" Source="sx1231skb\Doc\Packet handler\Message.html" Description="File successfully backed up as C:\Users\Coskun ERGAN\Desktop\FTDI_SPI\SX1231-master\Backup\sx1231skb\Doc\Packet handler\Message.html">
</Event><Event ErrorLevel="0" Project="sx1231skb" Source="sx1231skb\Doc\Packet handler\Node address.html" Description="File successfully backed up as C:\Users\Coskun ERGAN\Desktop\FTDI_SPI\SX1231-master\Backup\sx1231skb\Doc\Packet handler\Node address.html">
</Event><Event ErrorLevel="0" Project="sx1231skb" Source="sx1231skb\Doc\Packet handler\Packet format.html" Description="File successfully backed up as C:\Users\Coskun ERGAN\Desktop\FTDI_SPI\SX1231-master\Backup\sx1231skb\Doc\Packet handler\Packet format.html">
</Event><Event ErrorLevel="0" Project="sx1231skb" Source="sx1231skb\Doc\Packet handler\Payload length.html" Description="File successfully backed up as C:\Users\Coskun ERGAN\Desktop\FTDI_SPI\SX1231-master\Backup\sx1231skb\Doc\Packet handler\Payload length.html">
</Event><Event ErrorLevel="0" Project="sx1231skb" Source="sx1231skb\Doc\Packet handler\Preamble size.html" Description="File successfully backed up as C:\Users\Coskun ERGAN\Desktop\FTDI_SPI\SX1231-master\Backup\sx1231skb\Doc\Packet handler\Preamble size.html">
</Event><Event ErrorLevel="0" Project="sx1231skb" Source="sx1231skb\Doc\Packet handler\Repeat value.html" Description="File successfully backed up as C:\Users\Coskun ERGAN\Desktop\FTDI_SPI\SX1231-master\Backup\sx1231skb\Doc\Packet handler\Repeat value.html">
</Event><Event ErrorLevel="0" Project="sx1231skb" Source="sx1231skb\Doc\Packet handler\StartStop.html" Description="File successfully backed up as C:\Users\Coskun ERGAN\Desktop\FTDI_SPI\SX1231-master\Backup\sx1231skb\Doc\Packet handler\StartStop.html">
</Event><Event ErrorLevel="0" Project="sx1231skb" Source="sx1231skb\Doc\Packet handler\Sync word size.html" Description="File successfully backed up as C:\Users\Coskun ERGAN\Desktop\FTDI_SPI\SX1231-master\Backup\sx1231skb\Doc\Packet handler\Sync word size.html">
</Event><Event ErrorLevel="0" Project="sx1231skb" Source="sx1231skb\Doc\Packet handler\Sync word tolerance.html" Description="File successfully backed up as C:\Users\Coskun ERGAN\Desktop\FTDI_SPI\SX1231-master\Backup\sx1231skb\Doc\Packet handler\Sync word tolerance.html">
</Event><Event ErrorLevel="0" Project="sx1231skb" Source="sx1231skb\Doc\Packet handler\Sync word value.html" Description="File successfully backed up as C:\Users\Coskun ERGAN\Desktop\FTDI_SPI\SX1231-master\Backup\sx1231skb\Doc\Packet handler\Sync word value.html">
</Event><Event ErrorLevel="0" Project="sx1231skb" Source="sx1231skb\Doc\Packet handler\Sync word.html" Description="File successfully backed up as C:\Users\Coskun ERGAN\Desktop\FTDI_SPI\SX1231-master\Backup\sx1231skb\Doc\Packet handler\Sync word.html">
</Event><Event ErrorLevel="0" Project="sx1231skb" Source="sx1231skb\Doc\Packet handler\Tx packets.html" Description="File successfully backed up as C:\Users\Coskun ERGAN\Desktop\FTDI_SPI\SX1231-master\Backup\sx1231skb\Doc\Packet handler\Tx packets.html">
</Event><Event ErrorLevel="0" Project="sx1231skb" Source="sx1231skb\Doc\Packet handler\Tx start.html" Description="File successfully backed up as C:\Users\Coskun ERGAN\Desktop\FTDI_SPI\SX1231-master\Backup\sx1231skb\Doc\Packet handler\Tx start.html">
</Event><Event ErrorLevel="0" Project="sx1231skb" Source="sx1231skb\Doc\Receiver\Afc bandwidth.html" Description="File successfully backed up as C:\Users\Coskun ERGAN\Desktop\FTDI_SPI\SX1231-master\Backup\sx1231skb\Doc\Receiver\Afc bandwidth.html">
</Event><Event ErrorLevel="0" Project="sx1231skb" Source="sx1231skb\Doc\Receiver\Afc Fei.html" Description="File successfully backed up as C:\Users\Coskun ERGAN\Desktop\FTDI_SPI\SX1231-master\Backup\sx1231skb\Doc\Receiver\Afc Fei.html">
</Event><Event ErrorLevel="0" Project="sx1231skb" Source="sx1231skb\Doc\Receiver\Agc.html" Description="File successfully backed up as C:\Users\Coskun ERGAN\Desktop\FTDI_SPI\SX1231-master\Backup\sx1231skb\Doc\Receiver\Agc.html">
</Event><Event ErrorLevel="0" Project="sx1231skb" Source="sx1231skb\Doc\Receiver\Dagc.html" Description="File successfully backed up as C:\Users\Coskun ERGAN\Desktop\FTDI_SPI\SX1231-master\Backup\sx1231skb\Doc\Receiver\Dagc.html">
</Event><Event ErrorLevel="0" Project="sx1231skb" Source="sx1231skb\Doc\Receiver\Lna.html" Description="File successfully backed up as C:\Users\Coskun ERGAN\Desktop\FTDI_SPI\SX1231-master\Backup\sx1231skb\Doc\Receiver\Lna.html">
</Event><Event ErrorLevel="0" Project="sx1231skb" Source="sx1231skb\Doc\Receiver\Ook.html" Description="File successfully backed up as C:\Users\Coskun ERGAN\Desktop\FTDI_SPI\SX1231-master\Backup\sx1231skb\Doc\Receiver\Ook.html">
</Event><Event ErrorLevel="0" Project="sx1231skb" Source="sx1231skb\Doc\Receiver\Rssi.html" Description="File successfully backed up as C:\Users\Coskun ERGAN\Desktop\FTDI_SPI\SX1231-master\Backup\sx1231skb\Doc\Receiver\Rssi.html">
</Event><Event ErrorLevel="0" Project="sx1231skb" Source="sx1231skb\Doc\Receiver\Rx bandwidth.html" Description="File successfully backed up as C:\Users\Coskun ERGAN\Desktop\FTDI_SPI\SX1231-master\Backup\sx1231skb\Doc\Receiver\Rx bandwidth.html">
</Event><Event ErrorLevel="0" Project="sx1231skb" Source="sx1231skb\Doc\Temperature\Calibrate.html" Description="File successfully backed up as C:\Users\Coskun ERGAN\Desktop\FTDI_SPI\SX1231-master\Backup\sx1231skb\Doc\Temperature\Calibrate.html">
</Event><Event ErrorLevel="0" Project="sx1231skb" Source="sx1231skb\Doc\Temperature\Measure running.html" Description="File successfully backed up as C:\Users\Coskun ERGAN\Desktop\FTDI_SPI\SX1231-master\Backup\sx1231skb\Doc\Temperature\Measure running.html">
</Event><Event ErrorLevel="0" Project="sx1231skb" Source="sx1231skb\Doc\Temperature\Thermometer.html" Description="File successfully backed up as C:\Users\Coskun ERGAN\Desktop\FTDI_SPI\SX1231-master\Backup\sx1231skb\Doc\Temperature\Thermometer.html">
</Event><Event ErrorLevel="0" Project="sx1231skb" Source="sx1231skb\Doc\Transmitter\Output power.html" Description="File successfully backed up as C:\Users\Coskun ERGAN\Desktop\FTDI_SPI\SX1231-master\Backup\sx1231skb\Doc\Transmitter\Output power.html">
</Event><Event ErrorLevel="0" Project="sx1231skb" Source="sx1231skb\Doc\Transmitter\Overload current protection.html" Description="File successfully backed up as C:\Users\Coskun ERGAN\Desktop\FTDI_SPI\SX1231-master\Backup\sx1231skb\Doc\Transmitter\Overload current protection.html">
</Event><Event ErrorLevel="0" Project="sx1231skb" Source="sx1231skb\Doc\Transmitter\Power amplifier.html" Description="File successfully backed up as C:\Users\Coskun ERGAN\Desktop\FTDI_SPI\SX1231-master\Backup\sx1231skb\Doc\Transmitter\Power amplifier.html">
</Event><Event ErrorLevel="0" Project="sx1231skb" Source="sx1231skb\sx1231skb_usersguide.pdf" Description="File successfully backed up as C:\Users\Coskun ERGAN\Desktop\FTDI_SPI\SX1231-master\Backup\sx1231skb\sx1231skb_usersguide.pdf">
</Event><Event ErrorLevel="0" Project="sx1231skb" Source="sx1231skb\AboutBox.resx" Description="File successfully backed up as C:\Users\Coskun ERGAN\Desktop\FTDI_SPI\SX1231-master\Backup\sx1231skb\AboutBox.resx">
</Event><Event ErrorLevel="0" Project="sx1231skb" Source="sx1231skb\HelpForm.resx" Description="File successfully backed up as C:\Users\Coskun ERGAN\Desktop\FTDI_SPI\SX1231-master\Backup\sx1231skb\HelpForm.resx">
</Event><Event ErrorLevel="0" Project="sx1231skb" Source="sx1231skb\MainForm.resx" Description="File successfully backed up as C:\Users\Coskun ERGAN\Desktop\FTDI_SPI\SX1231-master\Backup\sx1231skb\MainForm.resx">
</Event><Event ErrorLevel="0" Project="sx1231skb" Source="sx1231skb\Properties\Resources.resx" Description="File successfully backed up as C:\Users\Coskun ERGAN\Desktop\FTDI_SPI\SX1231-master\Backup\sx1231skb\Properties\Resources.resx">
</Event><Event ErrorLevel="0" Project="sx1231skb" Source="sx1231skb\sx1231skb.csproj" Description="The project file does not require conversion.">
</Event><Event ErrorLevel="3" Project="sx1231skb" Source="sx1231skb\sx1231skb.csproj" Description="No Conversion Required">
</Event><Event ErrorLevel="0" Project="SemtechLib" Source="SemtechLib\SemtechLib.csproj" Description="Project file successfully backed up as C:\Users\Coskun ERGAN\Desktop\FTDI_SPI\SX1231-master\Backup\SemtechLib\SemtechLib.csproj">
</Event><Event ErrorLevel="0" Project="SemtechLib" Source="SemtechLib\AssemblyInfo.cs" Description="File successfully backed up as C:\Users\Coskun ERGAN\Desktop\FTDI_SPI\SX1231-master\Backup\SemtechLib\AssemblyInfo.cs">
</Event><Event ErrorLevel="0" Project="SemtechLib" Source="SemtechLib\Ftdi\FtdiInfo.cs" Description="File successfully backed up as C:\Users\Coskun ERGAN\Desktop\FTDI_SPI\SX1231-master\Backup\SemtechLib\Ftdi\FtdiInfo.cs">
</Event><Event ErrorLevel="0" Project="SemtechLib" Source="SemtechLib\General\Interfaces\INotifyDocumentationChanged.cs" Description="File successfully backed up as C:\Users\Coskun ERGAN\Desktop\FTDI_SPI\SX1231-master\Backup\SemtechLib\General\Interfaces\INotifyDocumentationChanged.cs">
</Event><Event ErrorLevel="0" Project="SemtechLib" Source="SemtechLib\General\Interfaces\DocumentationChangedEventArgs.cs" Description="File successfully backed up as C:\Users\Coskun ERGAN\Desktop\FTDI_SPI\SX1231-master\Backup\SemtechLib\General\Interfaces\DocumentationChangedEventArgs.cs">
</Event><Event ErrorLevel="0" Project="SemtechLib" Source="SemtechLib\General\Interfaces\DocumentationChangedEventHandler.cs" Description="File successfully backed up as C:\Users\Coskun ERGAN\Desktop\FTDI_SPI\SX1231-master\Backup\SemtechLib\General\Interfaces\DocumentationChangedEventHandler.cs">
</Event><Event ErrorLevel="0" Project="SemtechLib" Source="SemtechLib\Fusionbird\FusionToolkit\FusionTrackBar\TrackDrawModeEditor.cs" Description="File successfully backed up as C:\Users\Coskun ERGAN\Desktop\FTDI_SPI\SX1231-master\Backup\SemtechLib\Fusionbird\FusionToolkit\FusionTrackBar\TrackDrawModeEditor.cs">
</Event><Event ErrorLevel="0" Project="SemtechLib" Source="SemtechLib\Controls\HexBoxCtrl\HexCasing.cs" Description="File successfully backed up as C:\Users\Coskun ERGAN\Desktop\FTDI_SPI\SX1231-master\Backup\SemtechLib\Controls\HexBoxCtrl\HexCasing.cs">
</Event><Event ErrorLevel="0" Project="SemtechLib" Source="SemtechLib\Controls\HexBoxCtrl\BytePositionInfo.cs" Description="File successfully backed up as C:\Users\Coskun ERGAN\Desktop\FTDI_SPI\SX1231-master\Backup\SemtechLib\Controls\HexBoxCtrl\BytePositionInfo.cs">
</Event><Event ErrorLevel="0" Project="SemtechLib" Source="SemtechLib\Controls\HexBoxCtrl\HexBox.cs" Description="File successfully backed up as C:\Users\Coskun ERGAN\Desktop\FTDI_SPI\SX1231-master\Backup\SemtechLib\Controls\HexBoxCtrl\HexBox.cs">
</Event><Event ErrorLevel="0" Project="SemtechLib" Source="SemtechLib\General\TypeConverters\ObjectConverter.cs" Description="File successfully backed up as C:\Users\Coskun ERGAN\Desktop\FTDI_SPI\SX1231-master\Backup\SemtechLib\General\TypeConverters\ObjectConverter.cs">
</Event><Event ErrorLevel="0" Project="SemtechLib" Source="SemtechLib\General\Events\DecimalEventArg.cs" Description="File successfully backed up as C:\Users\Coskun ERGAN\Desktop\FTDI_SPI\SX1231-master\Backup\SemtechLib\General\Events\DecimalEventArg.cs">
</Event><Event ErrorLevel="0" Project="SemtechLib" Source="SemtechLib\General\Events\DecimalEventHandler.cs" Description="File successfully backed up as C:\Users\Coskun ERGAN\Desktop\FTDI_SPI\SX1231-master\Backup\SemtechLib\General\Events\DecimalEventHandler.cs">
</Event><Event ErrorLevel="0" Project="SemtechLib" Source="SemtechLib\General\EditableObject.cs" Description="File successfully backed up as C:\Users\Coskun ERGAN\Desktop\FTDI_SPI\SX1231-master\Backup\SemtechLib\General\EditableObject.cs">
</Event><Event ErrorLevel="0" Project="SemtechLib" Source="SemtechLib\General\BindingRegister.cs" Description="File successfully backed up as C:\Users\Coskun ERGAN\Desktop\FTDI_SPI\SX1231-master\Backup\SemtechLib\General\BindingRegister.cs">
</Event><Event ErrorLevel="0" Project="SemtechLib" Source="SemtechLib\Controls\TempCtrl.cs" Description="File successfully backed up as C:\Users\Coskun ERGAN\Desktop\FTDI_SPI\SX1231-master\Backup\SemtechLib\Controls\TempCtrl.cs">
</Event><Event ErrorLevel="0" Project="SemtechLib" Source="SemtechLib\Controls\PushBtn.cs" Description="File successfully backed up as C:\Users\Coskun ERGAN\Desktop\FTDI_SPI\SX1231-master\Backup\SemtechLib\Controls\PushBtn.cs">
</Event><Event ErrorLevel="0" Project="SemtechLib" Source="SemtechLib\Controls\Angle.cs" Description="File successfully backed up as C:\Users\Coskun ERGAN\Desktop\FTDI_SPI\SX1231-master\Backup\SemtechLib\Controls\Angle.cs">
</Event><Event ErrorLevel="0" Project="SemtechLib" Source="SemtechLib\DS\SimpleObjectConverter.cs" Description="File successfully backed up as C:\Users\Coskun ERGAN\Desktop\FTDI_SPI\SX1231-master\Backup\SemtechLib\DS\SimpleObjectConverter.cs">
</Event><Event ErrorLevel="0" Project="SemtechLib" Source="SemtechLib\TestIListSource2\OrderConverter.cs" Description="File successfully backed up as C:\Users\Coskun ERGAN\Desktop\FTDI_SPI\SX1231-master\Backup\SemtechLib\TestIListSource2\OrderConverter.cs">
</Event><Event ErrorLevel="0" Project="SemtechLib" Source="SemtechLib\DS\EditableObject.cs" Description="File successfully backed up as C:\Users\Coskun ERGAN\Desktop\FTDI_SPI\SX1231-master\Backup\SemtechLib\DS\EditableObject.cs">
</Event><Event ErrorLevel="0" Project="SemtechLib" Source="SemtechLib\TestIListSource2\Order.cs" Description="File successfully backed up as C:\Users\Coskun ERGAN\Desktop\FTDI_SPI\SX1231-master\Backup\SemtechLib\TestIListSource2\Order.cs">
</Event><Event ErrorLevel="0" Project="SemtechLib" Source="SemtechLib\TestIListSource2\ItemConverter.cs" Description="File successfully backed up as C:\Users\Coskun ERGAN\Desktop\FTDI_SPI\SX1231-master\Backup\SemtechLib\TestIListSource2\ItemConverter.cs">
</Event><Event ErrorLevel="0" Project="SemtechLib" Source="SemtechLib\TestIListSource2\Item.cs" Description="File successfully backed up as C:\Users\Coskun ERGAN\Desktop\FTDI_SPI\SX1231-master\Backup\SemtechLib\TestIListSource2\Item.cs">
</Event><Event ErrorLevel="0" Project="SemtechLib" Source="SemtechLib\DS\BindingCollectionBase.cs" Description="File successfully backed up as C:\Users\Coskun ERGAN\Desktop\FTDI_SPI\SX1231-master\Backup\SemtechLib\DS\BindingCollectionBase.cs">
</Event><Event ErrorLevel="0" Project="SemtechLib" Source="SemtechLib\TestIListSource2\OrderList.cs" Description="File successfully backed up as C:\Users\Coskun ERGAN\Desktop\FTDI_SPI\SX1231-master\Backup\SemtechLib\TestIListSource2\OrderList.cs">
</Event><Event ErrorLevel="0" Project="SemtechLib" Source="SemtechLib\TestIListSource2\ItemList.cs" Description="File successfully backed up as C:\Users\Coskun ERGAN\Desktop\FTDI_SPI\SX1231-master\Backup\SemtechLib\TestIListSource2\ItemList.cs">
</Event><Event ErrorLevel="0" Project="SemtechLib" Source="SemtechLib\TestIListSource2\TestSource.cs" Description="File successfully backed up as C:\Users\Coskun ERGAN\Desktop\FTDI_SPI\SX1231-master\Backup\SemtechLib\TestIListSource2\TestSource.cs">
</Event><Event ErrorLevel="0" Project="SemtechLib" Source="SemtechLib\General\Events\BooleanEventHandler.cs" Description="File successfully backed up as C:\Users\Coskun ERGAN\Desktop\FTDI_SPI\SX1231-master\Backup\SemtechLib\General\Events\BooleanEventHandler.cs">
</Event><Event ErrorLevel="0" Project="SemtechLib" Source="SemtechLib\General\Events\ProgressEventArg.cs" Description="File successfully backed up as C:\Users\Coskun ERGAN\Desktop\FTDI_SPI\SX1231-master\Backup\SemtechLib\General\Events\ProgressEventArg.cs">
</Event><Event ErrorLevel="0" Project="SemtechLib" Source="SemtechLib\General\Events\Int32EventArg.cs" Description="File successfully backed up as C:\Users\Coskun ERGAN\Desktop\FTDI_SPI\SX1231-master\Backup\SemtechLib\General\Events\Int32EventArg.cs">
</Event><Event ErrorLevel="0" Project="SemtechLib" Source="SemtechLib\Controls\Graph\GraphCtrl.cs" Description="File successfully backed up as C:\Users\Coskun ERGAN\Desktop\FTDI_SPI\SX1231-master\Backup\SemtechLib\Controls\Graph\GraphCtrl.cs">
</Event><Event ErrorLevel="0" Project="SemtechLib" Source="SemtechLib\DS\DSPropertyDescriptor.cs" Description="File successfully backed up as C:\Users\Coskun ERGAN\Desktop\FTDI_SPI\SX1231-master\Backup\SemtechLib\DS\DSPropertyDescriptor.cs">
</Event><Event ErrorLevel="0" Project="SemtechLib" Source="SemtechLib\DS\DSTypeDescriptor.cs" Description="File successfully backed up as C:\Users\Coskun ERGAN\Desktop\FTDI_SPI\SX1231-master\Backup\SemtechLib\DS\DSTypeDescriptor.cs">
</Event><Event ErrorLevel="0" Project="SemtechLib" Source="SemtechLib\DS\DSTypeDescriptorCollection.cs" Description="File successfully backed up as C:\Users\Coskun ERGAN\Desktop\FTDI_SPI\SX1231-master\Backup\SemtechLib\DS\DSTypeDescriptorCollection.cs">
</Event><Event ErrorLevel="0" Project="SemtechLib" Source="SemtechLib\Controls\ToolStripEx.cs" Description="File successfully backed up as C:\Users\Coskun ERGAN\Desktop\FTDI_SPI\SX1231-master\Backup\SemtechLib\Controls\ToolStripEx.cs">
</Event><Event ErrorLevel="0" Project="SemtechLib" Source="SemtechLib\Controls\HexBoxCtrl\DataBlock.cs" Description="File successfully backed up as C:\Users\Coskun ERGAN\Desktop\FTDI_SPI\SX1231-master\Backup\SemtechLib\Controls\HexBoxCtrl\DataBlock.cs">
</Event><Event ErrorLevel="0" Project="SemtechLib" Source="SemtechLib\Controls\HexBoxCtrl\FileDataBlock.cs" Description="File successfully backed up as C:\Users\Coskun ERGAN\Desktop\FTDI_SPI\SX1231-master\Backup\SemtechLib\Controls\HexBoxCtrl\FileDataBlock.cs">
</Event><Event ErrorLevel="0" Project="SemtechLib" Source="SemtechLib\Controls\HexBoxCtrl\IByteProvider.cs" Description="File successfully backed up as C:\Users\Coskun ERGAN\Desktop\FTDI_SPI\SX1231-master\Backup\SemtechLib\Controls\HexBoxCtrl\IByteProvider.cs">
</Event><Event ErrorLevel="0" Project="SemtechLib" Source="SemtechLib\Controls\HexBoxCtrl\FileByteProvider.cs" Description="File successfully backed up as C:\Users\Coskun ERGAN\Desktop\FTDI_SPI\SX1231-master\Backup\SemtechLib\Controls\HexBoxCtrl\FileByteProvider.cs">
</Event><Event ErrorLevel="0" Project="SemtechLib" Source="SemtechLib\Controls\HexBoxCtrl\Design\HexFontEditor.cs" Description="File successfully backed up as C:\Users\Coskun ERGAN\Desktop\FTDI_SPI\SX1231-master\Backup\SemtechLib\Controls\HexBoxCtrl\Design\HexFontEditor.cs">
</Event><Event ErrorLevel="0" Project="SemtechLib" Source="SemtechLib\General\TypeConverters\UInt16HexConverter.cs" Description="File successfully backed up as C:\Users\Coskun ERGAN\Desktop\FTDI_SPI\SX1231-master\Backup\SemtechLib\General\TypeConverters\UInt16HexConverter.cs">
</Event><Event ErrorLevel="0" Project="SemtechLib" Source="SemtechLib\General\Events\ByteEventHandler.cs" Description="File successfully backed up as C:\Users\Coskun ERGAN\Desktop\FTDI_SPI\SX1231-master\Backup\SemtechLib\General\Events\ByteEventHandler.cs">
</Event><Event ErrorLevel="0" Project="SemtechLib" Source="SemtechLib\General\Events\ByteArrayEventHandler.cs" Description="File successfully backed up as C:\Users\Coskun ERGAN\Desktop\FTDI_SPI\SX1231-master\Backup\SemtechLib\General\Events\ByteArrayEventHandler.cs">
</Event><Event ErrorLevel="0" Project="SemtechLib" Source="SemtechLib\General\CircularQueue.cs" Description="File successfully backed up as C:\Users\Coskun ERGAN\Desktop\FTDI_SPI\SX1231-master\Backup\SemtechLib\General\CircularQueue.cs">
</Event><Event ErrorLevel="0" Project="SemtechLib" Source="SemtechLib\Properties\Resources.cs" Description="File successfully backed up as C:\Users\Coskun ERGAN\Desktop\FTDI_SPI\SX1231-master\Backup\SemtechLib\Properties\Resources.cs">
</Event><Event ErrorLevel="0" Project="SemtechLib" Source="SemtechLib\General\Events\Int32EventHandler.cs" Description="File successfully backed up as C:\Users\Coskun ERGAN\Desktop\FTDI_SPI\SX1231-master\Backup\SemtechLib\General\Events\Int32EventHandler.cs">
</Event><Event ErrorLevel="0" Project="SemtechLib" Source="SemtechLib\Controls\MenuStripEx.cs" Description="File successfully backed up as C:\Users\Coskun ERGAN\Desktop\FTDI_SPI\SX1231-master\Backup\SemtechLib\Controls\MenuStripEx.cs">
</Event><Event ErrorLevel="0" Project="SemtechLib" Source="SemtechLib\Controls\GroupBoxEx.cs" Description="File successfully backed up as C:\Users\Coskun ERGAN\Desktop\FTDI_SPI\SX1231-master\Backup\SemtechLib\Controls\GroupBoxEx.cs">
</Event><Event ErrorLevel="0" Project="SemtechLib" Source="SemtechLib\General\RegisterCollection.cs" Description="File successfully backed up as C:\Users\Coskun ERGAN\Desktop\FTDI_SPI\SX1231-master\Backup\SemtechLib\General\RegisterCollection.cs">
</Event><Event ErrorLevel="0" Project="SemtechLib" Source="SemtechLib\General\Events\ErrorEventHandler.cs" Description="File successfully backed up as C:\Users\Coskun ERGAN\Desktop\FTDI_SPI\SX1231-master\Backup\SemtechLib\General\Events\ErrorEventHandler.cs">
</Event><Event ErrorLevel="0" Project="SemtechLib" Source="SemtechLib\General\ApplicationSettings.cs" Description="File successfully backed up as C:\Users\Coskun ERGAN\Desktop\FTDI_SPI\SX1231-master\Backup\SemtechLib\General\ApplicationSettings.cs">
</Event><Event ErrorLevel="0" Project="SemtechLib" Source="SemtechLib\Controls\SwitchBtn.cs" Description="File successfully backed up as C:\Users\Coskun ERGAN\Desktop\FTDI_SPI\SX1231-master\Backup\SemtechLib\Controls\SwitchBtn.cs">
</Event><Event ErrorLevel="0" Project="SemtechLib" Source="SemtechLib\Fusionbird\FusionToolkit\FusionTrackBar\TrackBarItemState.cs" Description="File successfully backed up as C:\Users\Coskun ERGAN\Desktop\FTDI_SPI\SX1231-master\Backup\SemtechLib\Fusionbird\FusionToolkit\FusionTrackBar\TrackBarItemState.cs">
</Event><Event ErrorLevel="0" Project="SemtechLib" Source="SemtechLib\Controls\HexBoxCtrl\DataMap.cs" Description="File successfully backed up as C:\Users\Coskun ERGAN\Desktop\FTDI_SPI\SX1231-master\Backup\SemtechLib\Controls\HexBoxCtrl\DataMap.cs">
</Event><Event ErrorLevel="0" Project="SemtechLib" Source="SemtechLib\Controls\ToolStripLed.cs" Description="File successfully backed up as C:\Users\Coskun ERGAN\Desktop\FTDI_SPI\SX1231-master\Backup\SemtechLib\Controls\ToolStripLed.cs">
</Event><Event ErrorLevel="0" Project="SemtechLib" Source="SemtechLib\Fusionbird\FusionToolkit\FusionTrackBar\TrackBarOwnerDrawParts.cs" Description="File successfully backed up as C:\Users\Coskun ERGAN\Desktop\FTDI_SPI\SX1231-master\Backup\SemtechLib\Fusionbird\FusionToolkit\FusionTrackBar\TrackBarOwnerDrawParts.cs">
</Event><Event ErrorLevel="0" Project="SemtechLib" Source="SemtechLib\General\Events\ProgressEventHandler.cs" Description="File successfully backed up as C:\Users\Coskun ERGAN\Desktop\FTDI_SPI\SX1231-master\Backup\SemtechLib\General\Events\ProgressEventHandler.cs">
</Event><Event ErrorLevel="0" Project="SemtechLib" Source="SemtechLib\Ftdi\FtdiIoPort.cs" Description="File successfully backed up as C:\Users\Coskun ERGAN\Desktop\FTDI_SPI\SX1231-master\Backup\SemtechLib\Ftdi\FtdiIoPort.cs">
</Event><Event ErrorLevel="0" Project="SemtechLib" Source="SemtechLib\Ftdi\Mpsse.cs" Description="File successfully backed up as C:\Users\Coskun ERGAN\Desktop\FTDI_SPI\SX1231-master\Backup\SemtechLib\Ftdi\Mpsse.cs">
</Event><Event ErrorLevel="0" Project="SemtechLib" Source="SemtechLib\Ftdi\MpsseSPI.cs" Description="File successfully backed up as C:\Users\Coskun ERGAN\Desktop\FTDI_SPI\SX1231-master\Backup\SemtechLib\Ftdi\MpsseSPI.cs">
</Event><Event ErrorLevel="0" Project="SemtechLib" Source="SemtechLib\Controls\VProgressBar.cs" Description="File successfully backed up as C:\Users\Coskun ERGAN\Desktop\FTDI_SPI\SX1231-master\Backup\SemtechLib\Controls\VProgressBar.cs">
</Event><Event ErrorLevel="0" Project="SemtechLib" Source="SemtechLib\Fusionbird\FusionToolkit\FusionTrackBar\FusionTrackBar.cs" Description="File successfully backed up as C:\Users\Coskun ERGAN\Desktop\FTDI_SPI\SX1231-master\Backup\SemtechLib\Fusionbird\FusionToolkit\FusionTrackBar\FusionTrackBar.cs">
</Event><Event ErrorLevel="0" Project="SemtechLib" Source="SemtechLib\Controls\Led.cs" Description="File successfully backed up as C:\Users\Coskun ERGAN\Desktop\FTDI_SPI\SX1231-master\Backup\SemtechLib\Controls\Led.cs">
</Event><Event ErrorLevel="0" Project="SemtechLib" Source="SemtechLib\Controls\HexBoxCtrl\ByteCollection.cs" Description="File successfully backed up as C:\Users\Coskun ERGAN\Desktop\FTDI_SPI\SX1231-master\Backup\SemtechLib\Controls\HexBoxCtrl\ByteCollection.cs">
</Event><Event ErrorLevel="0" Project="SemtechLib" Source="SemtechLib\Microsoft\Win32\NativeConstants.cs" Description="File successfully backed up as C:\Users\Coskun ERGAN\Desktop\FTDI_SPI\SX1231-master\Backup\SemtechLib\Microsoft\Win32\NativeConstants.cs">
</Event><Event ErrorLevel="0" Project="SemtechLib" Source="SemtechLib\Controls\NumericUpDownEx.cs" Description="File successfully backed up as C:\Users\Coskun ERGAN\Desktop\FTDI_SPI\SX1231-master\Backup\SemtechLib\Controls\NumericUpDownEx.cs">
</Event><Event ErrorLevel="0" Project="SemtechLib" Source="SemtechLib\General\Events\ByteEventArg.cs" Description="File successfully backed up as C:\Users\Coskun ERGAN\Desktop\FTDI_SPI\SX1231-master\Backup\SemtechLib\General\Events\ByteEventArg.cs">
</Event><Event ErrorLevel="0" Project="SemtechLib" Source="SemtechLib\General\Register.cs" Description="File successfully backed up as C:\Users\Coskun ERGAN\Desktop\FTDI_SPI\SX1231-master\Backup\SemtechLib\General\Register.cs">
</Event><Event ErrorLevel="0" Project="SemtechLib" Source="SemtechLib\Fusionbird\FusionToolkit\FusionTrackBar\TrackBarDrawItemEventArgs.cs" Description="File successfully backed up as C:\Users\Coskun ERGAN\Desktop\FTDI_SPI\SX1231-master\Backup\SemtechLib\Fusionbird\FusionToolkit\FusionTrackBar\TrackBarDrawItemEventArgs.cs">
</Event><Event ErrorLevel="0" Project="SemtechLib" Source="SemtechLib\Controls\HexBoxCtrl\NativeMethods.cs" Description="File successfully backed up as C:\Users\Coskun ERGAN\Desktop\FTDI_SPI\SX1231-master\Backup\SemtechLib\Controls\HexBoxCtrl\NativeMethods.cs">
</Event><Event ErrorLevel="0" Project="SemtechLib" Source="SemtechLib\General\TypeConverters\UInt32HexConverter.cs" Description="File successfully backed up as C:\Users\Coskun ERGAN\Desktop\FTDI_SPI\SX1231-master\Backup\SemtechLib\General\TypeConverters\UInt32HexConverter.cs">
</Event><Event ErrorLevel="0" Project="SemtechLib" Source="SemtechLib\General\TypeConverters\ByteHexConverter.cs" Description="File successfully backed up as C:\Users\Coskun ERGAN\Desktop\FTDI_SPI\SX1231-master\Backup\SemtechLib\General\TypeConverters\ByteHexConverter.cs">
</Event><Event ErrorLevel="0" Project="SemtechLib" Source="SemtechLib\General\Events\DoubleEventArg.cs" Description="File successfully backed up as C:\Users\Coskun ERGAN\Desktop\FTDI_SPI\SX1231-master\Backup\SemtechLib\General\Events\DoubleEventArg.cs">
</Event><Event ErrorLevel="0" Project="SemtechLib" Source="SemtechLib\General\Events\ByteArrayEventArg.cs" Description="File successfully backed up as C:\Users\Coskun ERGAN\Desktop\FTDI_SPI\SX1231-master\Backup\SemtechLib\General\Events\ByteArrayEventArg.cs">
</Event><Event ErrorLevel="0" Project="SemtechLib" Source="SemtechLib\Controls\HexBoxCtrl\DynamicFileByteProvider.cs" Description="File successfully backed up as C:\Users\Coskun ERGAN\Desktop\FTDI_SPI\SX1231-master\Backup\SemtechLib\Controls\HexBoxCtrl\DynamicFileByteProvider.cs">
</Event><Event ErrorLevel="0" Project="SemtechLib" Source="SemtechLib\General\BindingCollectionBase.cs" Description="File successfully backed up as C:\Users\Coskun ERGAN\Desktop\FTDI_SPI\SX1231-master\Backup\SemtechLib\General\BindingCollectionBase.cs">
</Event><Event ErrorLevel="0" Project="SemtechLib" Source="SemtechLib\Controls\HexBoxCtrl\MemoryDataBlock.cs" Description="File successfully backed up as C:\Users\Coskun ERGAN\Desktop\FTDI_SPI\SX1231-master\Backup\SemtechLib\Controls\HexBoxCtrl\MemoryDataBlock.cs">
</Event><Event ErrorLevel="0" Project="SemtechLib" Source="SemtechLib\Ftdi\FtdiDevice.cs" Description="File successfully backed up as C:\Users\Coskun ERGAN\Desktop\FTDI_SPI\SX1231-master\Backup\SemtechLib\Ftdi\FtdiDevice.cs">
</Event><Event ErrorLevel="0" Project="SemtechLib" Source="SemtechLib\Ftdi\IoPort.cs" Description="File successfully backed up as C:\Users\Coskun ERGAN\Desktop\FTDI_SPI\SX1231-master\Backup\SemtechLib\Ftdi\IoPort.cs">
</Event><Event ErrorLevel="0" Project="SemtechLib" Source="SemtechLib\General\Events\DoubleEventHandler.cs" Description="File successfully backed up as C:\Users\Coskun ERGAN\Desktop\FTDI_SPI\SX1231-master\Backup\SemtechLib\General\Events\DoubleEventHandler.cs">
</Event><Event ErrorLevel="0" Project="SemtechLib" Source="SemtechLib\General\Events\ErrorEventArgs.cs" Description="File successfully backed up as C:\Users\Coskun ERGAN\Desktop\FTDI_SPI\SX1231-master\Backup\SemtechLib\General\Events\ErrorEventArgs.cs">
</Event><Event ErrorLevel="0" Project="SemtechLib" Source="SemtechLib\General\BindingRegisterList.cs" Description="File successfully backed up as C:\Users\Coskun ERGAN\Desktop\FTDI_SPI\SX1231-master\Backup\SemtechLib\General\BindingRegisterList.cs">
</Event><Event ErrorLevel="0" Project="SemtechLib" Source="SemtechLib\Controls\Jumper.cs" Description="File successfully backed up as C:\Users\Coskun ERGAN\Desktop\FTDI_SPI\SX1231-master\Backup\SemtechLib\Controls\Jumper.cs">
</Event><Event ErrorLevel="0" Project="SemtechLib" Source="SemtechLib\Controls\HexBoxCtrl\DynamicByteProvider.cs" Description="File successfully backed up as C:\Users\Coskun ERGAN\Desktop\FTDI_SPI\SX1231-master\Backup\SemtechLib\Controls\HexBoxCtrl\DynamicByteProvider.cs">
</Event><Event ErrorLevel="0" Project="SemtechLib" Source="SemtechLib\General\PropertySorter.cs" Description="File successfully backed up as C:\Users\Coskun ERGAN\Desktop\FTDI_SPI\SX1231-master\Backup\SemtechLib\General\PropertySorter.cs">
</Event><Event ErrorLevel="0" Project="SemtechLib" Source="SemtechLib\General\PropertyOrderAttribute.cs" Description="File successfully backed up as C:\Users\Coskun ERGAN\Desktop\FTDI_SPI\SX1231-master\Backup\SemtechLib\General\PropertyOrderAttribute.cs">
</Event><Event ErrorLevel="0" Project="SemtechLib" Source="SemtechLib\General\PropertyOrderPair.cs" Description="File successfully backed up as C:\Users\Coskun ERGAN\Desktop\FTDI_SPI\SX1231-master\Backup\SemtechLib\General\PropertyOrderPair.cs">
</Event><Event ErrorLevel="0" Project="SemtechLib" Source="SemtechLib\Ftdi\MpsseI2C.cs" Description="File successfully backed up as C:\Users\Coskun ERGAN\Desktop\FTDI_SPI\SX1231-master\Backup\SemtechLib\Ftdi\MpsseI2C.cs">
</Event><Event ErrorLevel="0" Project="SemtechLib" Source="SemtechLib\Fusionbird\FusionToolkit\NativeMethods.cs" Description="File successfully backed up as C:\Users\Coskun ERGAN\Desktop\FTDI_SPI\SX1231-master\Backup\SemtechLib\Fusionbird\FusionToolkit\NativeMethods.cs">
</Event><Event ErrorLevel="0" Project="SemtechLib" Source="SemtechLib\General\Events\BooleanEventArg.cs" Description="File successfully backed up as C:\Users\Coskun ERGAN\Desktop\FTDI_SPI\SX1231-master\Backup\SemtechLib\General\Events\BooleanEventArg.cs">
</Event><Event ErrorLevel="0" Project="SemtechLib" Source="SemtechLib\Controls\Graph\GraphCtrl.resx" Description="File successfully backed up as C:\Users\Coskun ERGAN\Desktop\FTDI_SPI\SX1231-master\Backup\SemtechLib\Controls\Graph\GraphCtrl.resx">
</Event><Event ErrorLevel="0" Project="SemtechLib" Source="SemtechLib\Controls\HexBoxCtrl\HexBox.resx" Description="File successfully backed up as C:\Users\Coskun ERGAN\Desktop\FTDI_SPI\SX1231-master\Backup\SemtechLib\Controls\HexBoxCtrl\HexBox.resx">
</Event><Event ErrorLevel="0" Project="SemtechLib" Source="SemtechLib\Properties\Resources.resx" Description="File successfully backed up as C:\Users\Coskun ERGAN\Desktop\FTDI_SPI\SX1231-master\Backup\SemtechLib\Properties\Resources.resx">
</Event><Event ErrorLevel="0" Project="SemtechLib" Source="SemtechLib\SemtechLib.csproj" Description="The project file does not require conversion.">
</Event><Event ErrorLevel="3" Project="SemtechLib" Source="SemtechLib\SemtechLib.csproj" Description="No Conversion Required">
</Event><Event ErrorLevel="0" Project="SemtechLib.Devices.SX1231" Source="SemtechLib.Devices.SX1231\SemtechLib.Devices.SX1231.csproj" Description="Project file successfully backed up as C:\Users\Coskun ERGAN\Desktop\FTDI_SPI\SX1231-master\Backup\SemtechLib.Devices.SX1231\SemtechLib.Devices.SX1231.csproj">
</Event><Event ErrorLevel="0" Project="SemtechLib.Devices.SX1231" Source="SemtechLib.Devices.SX1231\AssemblyInfo.cs" Description="File successfully backed up as C:\Users\Coskun ERGAN\Desktop\FTDI_SPI\SX1231-master\Backup\SemtechLib.Devices.SX1231\AssemblyInfo.cs">
</Event><Event ErrorLevel="0" Project="SemtechLib.Devices.SX1231" Source="SemtechLib.Devices.SX1231\Events\DcFreeEventArg.cs" Description="File successfully backed up as C:\Users\Coskun ERGAN\Desktop\FTDI_SPI\SX1231-master\Backup\SemtechLib.Devices.SX1231\Events\DcFreeEventArg.cs">
</Event><Event ErrorLevel="0" Project="SemtechLib.Devices.SX1231" Source="SemtechLib.Devices.SX1231\Events\AgcStepEventArg.cs" Description="File successfully backed up as C:\Users\Coskun ERGAN\Desktop\FTDI_SPI\SX1231-master\Backup\SemtechLib.Devices.SX1231\Events\AgcStepEventArg.cs">
</Event><Event ErrorLevel="0" Project="SemtechLib.Devices.SX1231" Source="SemtechLib.Devices.SX1231\Enumerations\ModulationTypeEnum.cs" Description="File successfully backed up as C:\Users\Coskun ERGAN\Desktop\FTDI_SPI\SX1231-master\Backup\SemtechLib.Devices.SX1231\Enumerations\ModulationTypeEnum.cs">
</Event><Event ErrorLevel="0" Project="SemtechLib.Devices.SX1231" Source="SemtechLib.Devices.SX1231\Enumerations\OokPeakThreshStepEnum.cs" Description="File successfully backed up as C:\Users\Coskun ERGAN\Desktop\FTDI_SPI\SX1231-master\Backup\SemtechLib.Devices.SX1231\Enumerations\OokPeakThreshStepEnum.cs">
</Event><Event ErrorLevel="0" Project="SemtechLib.Devices.SX1231" Source="SemtechLib.Devices.SX1231\Enumerations\IntermediateModeEnum.cs" Description="File successfully backed up as C:\Users\Coskun ERGAN\Desktop\FTDI_SPI\SX1231-master\Backup\SemtechLib.Devices.SX1231\Enumerations\IntermediateModeEnum.cs">
</Event><Event ErrorLevel="0" Project="SemtechLib.Devices.SX1231" Source="SemtechLib.Devices.SX1231\Forms\TestForm.cs" Description="File successfully backed up as C:\Users\Coskun ERGAN\Desktop\FTDI_SPI\SX1231-master\Backup\SemtechLib.Devices.SX1231\Forms\TestForm.cs">
</Event><Event ErrorLevel="0" Project="SemtechLib.Devices.SX1231" Source="SemtechLib.Devices.SX1231\Controls\TemperatureViewControl.cs" Description="File successfully backed up as C:\Users\Coskun ERGAN\Desktop\FTDI_SPI\SX1231-master\Backup\SemtechLib.Devices.SX1231\Controls\TemperatureViewControl.cs">
</Event><Event ErrorLevel="0" Project="SemtechLib.Devices.SX1231" Source="SemtechLib.Devices.SX1231\Events\LnaZinEventHandler.cs" Description="File successfully backed up as C:\Users\Coskun ERGAN\Desktop\FTDI_SPI\SX1231-master\Backup\SemtechLib.Devices.SX1231\Events\LnaZinEventHandler.cs">
</Event><Event ErrorLevel="0" Project="SemtechLib.Devices.SX1231" Source="SemtechLib.Devices.SX1231\Events\LimitCheckStatusEventHandler.cs" Description="File successfully backed up as C:\Users\Coskun ERGAN\Desktop\FTDI_SPI\SX1231-master\Backup\SemtechLib.Devices.SX1231\Events\LimitCheckStatusEventHandler.cs">
</Event><Event ErrorLevel="0" Project="SemtechLib.Devices.SX1231" Source="SemtechLib.Devices.SX1231\Events\EnterConditionEventArg.cs" Description="File successfully backed up as C:\Users\Coskun ERGAN\Desktop\FTDI_SPI\SX1231-master\Backup\SemtechLib.Devices.SX1231\Events\EnterConditionEventArg.cs">
</Event><Event ErrorLevel="0" Project="SemtechLib.Devices.SX1231" Source="SemtechLib.Devices.SX1231\Enumerations\OperatingModeEnum.cs" Description="File successfully backed up as C:\Users\Coskun ERGAN\Desktop\FTDI_SPI\SX1231-master\Backup\SemtechLib.Devices.SX1231\Enumerations\OperatingModeEnum.cs">
</Event><Event ErrorLevel="0" Project="SemtechLib.Devices.SX1231" Source="SemtechLib.Devices.SX1231\Enumerations\LnaZinEnum.cs" Description="File successfully backed up as C:\Users\Coskun ERGAN\Desktop\FTDI_SPI\SX1231-master\Backup\SemtechLib.Devices.SX1231\Enumerations\LnaZinEnum.cs">
</Event><Event ErrorLevel="0" Project="SemtechLib.Devices.SX1231" Source="SemtechLib.Devices.SX1231\Enumerations\LnaGainEnum.cs" Description="File successfully backed up as C:\Users\Coskun ERGAN\Desktop\FTDI_SPI\SX1231-master\Backup\SemtechLib.Devices.SX1231\Enumerations\LnaGainEnum.cs">
</Event><Event ErrorLevel="0" Project="SemtechLib.Devices.SX1231" Source="SemtechLib.Devices.SX1231\Forms\RssiAnalyserForm.cs" Description="File successfully backed up as C:\Users\Coskun ERGAN\Desktop\FTDI_SPI\SX1231-master\Backup\SemtechLib.Devices.SX1231\Forms\RssiAnalyserForm.cs">
</Event><Event ErrorLevel="0" Project="SemtechLib.Devices.SX1231" Source="SemtechLib.Devices.SX1231\Events\LimitCheckStatusEventArg.cs" Description="File successfully backed up as C:\Users\Coskun ERGAN\Desktop\FTDI_SPI\SX1231-master\Backup\SemtechLib.Devices.SX1231\Events\LimitCheckStatusEventArg.cs">
</Event><Event ErrorLevel="0" Project="SemtechLib.Devices.SX1231" Source="SemtechLib.Devices.SX1231\Enumerations\LowBatTrimEnum.cs" Description="File successfully backed up as C:\Users\Coskun ERGAN\Desktop\FTDI_SPI\SX1231-master\Backup\SemtechLib.Devices.SX1231\Enumerations\LowBatTrimEnum.cs">
</Event><Event ErrorLevel="0" Project="SemtechLib.Devices.SX1231" Source="SemtechLib.Devices.SX1231\Enumerations\ListenEndEnum.cs" Description="File successfully backed up as C:\Users\Coskun ERGAN\Desktop\FTDI_SPI\SX1231-master\Backup\SemtechLib.Devices.SX1231\Enumerations\ListenEndEnum.cs">
</Event><Event ErrorLevel="0" Project="SemtechLib.Devices.SX1231" Source="SemtechLib.Devices.SX1231\Controls\PacketHandlerView.cs" Description="File successfully backed up as C:\Users\Coskun ERGAN\Desktop\FTDI_SPI\SX1231-master\Backup\SemtechLib.Devices.SX1231\Controls\PacketHandlerView.cs">
</Event><Event ErrorLevel="0" Project="SemtechLib.Devices.SX1231" Source="SemtechLib.Devices.SX1231\Forms\TemperatureCalibrationForm.cs" Description="File successfully backed up as C:\Users\Coskun ERGAN\Desktop\FTDI_SPI\SX1231-master\Backup\SemtechLib.Devices.SX1231\Forms\TemperatureCalibrationForm.cs">
</Event><Event ErrorLevel="0" Project="SemtechLib.Devices.SX1231" Source="SemtechLib.Devices.SX1231\Events\PacketStatusEventHandler.cs" Description="File successfully backed up as C:\Users\Coskun ERGAN\Desktop\FTDI_SPI\SX1231-master\Backup\SemtechLib.Devices.SX1231\Events\PacketStatusEventHandler.cs">
</Event><Event ErrorLevel="0" Project="SemtechLib.Devices.SX1231" Source="SemtechLib.Devices.SX1231\Controls\CommonViewControl.cs" Description="File successfully backed up as C:\Users\Coskun ERGAN\Desktop\FTDI_SPI\SX1231-master\Backup\SemtechLib.Devices.SX1231\Controls\CommonViewControl.cs">
</Event><Event ErrorLevel="0" Project="SemtechLib.Devices.SX1231" Source="SemtechLib.Devices.SX1231\Enumerations\OokThreshTypeEnum.cs" Description="File successfully backed up as C:\Users\Coskun ERGAN\Desktop\FTDI_SPI\SX1231-master\Backup\SemtechLib.Devices.SX1231\Enumerations\OokThreshTypeEnum.cs">
</Event><Event ErrorLevel="0" Project="SemtechLib.Devices.SX1231" Source="SemtechLib.Devices.SX1231\Controls\IrqMapViewControl.cs" Description="File successfully backed up as C:\Users\Coskun ERGAN\Desktop\FTDI_SPI\SX1231-master\Backup\SemtechLib.Devices.SX1231\Controls\IrqMapViewControl.cs">
</Event><Event ErrorLevel="0" Project="SemtechLib.Devices.SX1231" Source="SemtechLib.Devices.SX1231\Events\EnterConditionEventHandler.cs" Description="File successfully backed up as C:\Users\Coskun ERGAN\Desktop\FTDI_SPI\SX1231-master\Backup\SemtechLib.Devices.SX1231\Events\EnterConditionEventHandler.cs">
</Event><Event ErrorLevel="0" Project="SemtechLib.Devices.SX1231" Source="SemtechLib.Devices.SX1231\Properties\Resources.cs" Description="File successfully backed up as C:\Users\Coskun ERGAN\Desktop\FTDI_SPI\SX1231-master\Backup\SemtechLib.Devices.SX1231\Properties\Resources.cs">
</Event><Event ErrorLevel="0" Project="SemtechLib.Devices.SX1231" Source="SemtechLib.Devices.SX1231\Events\LnaGainEventArg.cs" Description="File successfully backed up as C:\Users\Coskun ERGAN\Desktop\FTDI_SPI\SX1231-master\Backup\SemtechLib.Devices.SX1231\Events\LnaGainEventArg.cs">
</Event><Event ErrorLevel="0" Project="SemtechLib.Devices.SX1231" Source="SemtechLib.Devices.SX1231\Controls\TransmitterViewControl.cs" Description="File successfully backed up as C:\Users\Coskun ERGAN\Desktop\FTDI_SPI\SX1231-master\Backup\SemtechLib.Devices.SX1231\Controls\TransmitterViewControl.cs">
</Event><Event ErrorLevel="0" Project="SemtechLib.Devices.SX1231" Source="SemtechLib.Devices.SX1231\Controls\RssiGraphControl.cs" Description="File successfully backed up as C:\Users\Coskun ERGAN\Desktop\FTDI_SPI\SX1231-master\Backup\SemtechLib.Devices.SX1231\Controls\RssiGraphControl.cs">
</Event><Event ErrorLevel="0" Project="SemtechLib.Devices.SX1231" Source="SemtechLib.Devices.SX1231\Forms\SpectrumAnalyserForm.cs" Description="File successfully backed up as C:\Users\Coskun ERGAN\Desktop\FTDI_SPI\SX1231-master\Backup\SemtechLib.Devices.SX1231\Forms\SpectrumAnalyserForm.cs">
</Event><Event ErrorLevel="0" Project="SemtechLib.Devices.SX1231" Source="SemtechLib.Devices.SX1231\Forms\PacketLogForm.cs" Description="File successfully backed up as C:\Users\Coskun ERGAN\Desktop\FTDI_SPI\SX1231-master\Backup\SemtechLib.Devices.SX1231\Forms\PacketLogForm.cs">
</Event><Event ErrorLevel="0" Project="SemtechLib.Devices.SX1231" Source="SemtechLib.Devices.SX1231\Enumerations\DataModeEnum.cs" Description="File successfully backed up as C:\Users\Coskun ERGAN\Desktop\FTDI_SPI\SX1231-master\Backup\SemtechLib.Devices.SX1231\Enumerations\DataModeEnum.cs">
</Event><Event ErrorLevel="0" Project="SemtechLib.Devices.SX1231" Source="SemtechLib.Devices.SX1231\Enumerations\DioMappingEnum.cs" Description="File successfully backed up as C:\Users\Coskun ERGAN\Desktop\FTDI_SPI\SX1231-master\Backup\SemtechLib.Devices.SX1231\Enumerations\DioMappingEnum.cs">
</Event><Event ErrorLevel="0" Project="SemtechLib.Devices.SX1231" Source="SemtechLib.Devices.SX1231\Controls\DeviceViewControl.cs" Description="File successfully backed up as C:\Users\Coskun ERGAN\Desktop\FTDI_SPI\SX1231-master\Backup\SemtechLib.Devices.SX1231\Controls\DeviceViewControl.cs">
</Event><Event ErrorLevel="0" Project="SemtechLib.Devices.SX1231" Source="SemtechLib.Devices.SX1231\Controls\SpectrumGraphControl.cs" Description="File successfully backed up as C:\Users\Coskun ERGAN\Desktop\FTDI_SPI\SX1231-master\Backup\SemtechLib.Devices.SX1231\Controls\SpectrumGraphControl.cs">
</Event><Event ErrorLevel="0" Project="SemtechLib.Devices.SX1231" Source="SemtechLib.Devices.SX1231\SX1231.cs" Description="File successfully backed up as C:\Users\Coskun ERGAN\Desktop\FTDI_SPI\SX1231-master\Backup\SemtechLib.Devices.SX1231\SX1231.cs">
</Event><Event ErrorLevel="0" Project="SemtechLib.Devices.SX1231" Source="SemtechLib.Devices.SX1231\Events\OokPeakThreshDecEventArg.cs" Description="File successfully backed up as C:\Users\Coskun ERGAN\Desktop\FTDI_SPI\SX1231-master\Backup\SemtechLib.Devices.SX1231\Events\OokPeakThreshDecEventArg.cs">
</Event><Event ErrorLevel="0" Project="SemtechLib.Devices.SX1231" Source="SemtechLib.Devices.SX1231\Enumerations\ListenCriteriaEnum.cs" Description="File successfully backed up as C:\Users\Coskun ERGAN\Desktop\FTDI_SPI\SX1231-master\Backup\SemtechLib.Devices.SX1231\Enumerations\ListenCriteriaEnum.cs">
</Event><Event ErrorLevel="0" Project="SemtechLib.Devices.SX1231" Source="SemtechLib.Devices.SX1231\Controls\RegisterTableControl.cs" Description="File successfully backed up as C:\Users\Coskun ERGAN\Desktop\FTDI_SPI\SX1231-master\Backup\SemtechLib.Devices.SX1231\Controls\RegisterTableControl.cs">
</Event><Event ErrorLevel="0" Project="SemtechLib.Devices.SX1231" Source="SemtechLib.Devices.SX1231\Forms\RegistersForm.cs" Description="File successfully backed up as C:\Users\Coskun ERGAN\Desktop\FTDI_SPI\SX1231-master\Backup\SemtechLib.Devices.SX1231\Forms\RegistersForm.cs">
</Event><Event ErrorLevel="0" Project="SemtechLib.Devices.SX1231" Source="SemtechLib.Devices.SX1231\Events\PaRampEventHandler.cs" Description="File successfully backed up as C:\Users\Coskun ERGAN\Desktop\FTDI_SPI\SX1231-master\Backup\SemtechLib.Devices.SX1231\Events\PaRampEventHandler.cs">
</Event><Event ErrorLevel="0" Project="SemtechLib.Devices.SX1231" Source="SemtechLib.Devices.SX1231\Events\ListenEndEventHandler.cs" Description="File successfully backed up as C:\Users\Coskun ERGAN\Desktop\FTDI_SPI\SX1231-master\Backup\SemtechLib.Devices.SX1231\Events\ListenEndEventHandler.cs">
</Event><Event ErrorLevel="0" Project="SemtechLib.Devices.SX1231" Source="SemtechLib.Devices.SX1231\Events\DcFreeEventHandler.cs" Description="File successfully backed up as C:\Users\Coskun ERGAN\Desktop\FTDI_SPI\SX1231-master\Backup\SemtechLib.Devices.SX1231\Events\DcFreeEventHandler.cs">
</Event><Event ErrorLevel="0" Project="SemtechLib.Devices.SX1231" Source="SemtechLib.Devices.SX1231\Events\FifoFillConditionEventArg.cs" Description="File successfully backed up as C:\Users\Coskun ERGAN\Desktop\FTDI_SPI\SX1231-master\Backup\SemtechLib.Devices.SX1231\Events\FifoFillConditionEventArg.cs">
</Event><Event ErrorLevel="0" Project="SemtechLib.Devices.SX1231" Source="SemtechLib.Devices.SX1231\Enumerations\PaModeEnum.cs" Description="File successfully backed up as C:\Users\Coskun ERGAN\Desktop\FTDI_SPI\SX1231-master\Backup\SemtechLib.Devices.SX1231\Enumerations\PaModeEnum.cs">
</Event><Event ErrorLevel="0" Project="SemtechLib.Devices.SX1231" Source="SemtechLib.Devices.SX1231\Events\OokThreshTypeEventHandler.cs" Description="File successfully backed up as C:\Users\Coskun ERGAN\Desktop\FTDI_SPI\SX1231-master\Backup\SemtechLib.Devices.SX1231\Events\OokThreshTypeEventHandler.cs">
</Event><Event ErrorLevel="0" Project="SemtechLib.Devices.SX1231" Source="SemtechLib.Devices.SX1231\Events\FifoFillConditionEventHandler.cs" Description="File successfully backed up as C:\Users\Coskun ERGAN\Desktop\FTDI_SPI\SX1231-master\Backup\SemtechLib.Devices.SX1231\Events\FifoFillConditionEventHandler.cs">
</Event><Event ErrorLevel="0" Project="SemtechLib.Devices.SX1231" Source="SemtechLib.Devices.SX1231\Events\AddressFilteringEventHandler.cs" Description="File successfully backed up as C:\Users\Coskun ERGAN\Desktop\FTDI_SPI\SX1231-master\Backup\SemtechLib.Devices.SX1231\Events\AddressFilteringEventHandler.cs">
</Event><Event ErrorLevel="0" Project="SemtechLib.Devices.SX1231" Source="SemtechLib.Devices.SX1231\Events\OokAverageThreshFiltEventArg.cs" Description="File successfully backed up as C:\Users\Coskun ERGAN\Desktop\FTDI_SPI\SX1231-master\Backup\SemtechLib.Devices.SX1231\Events\OokAverageThreshFiltEventArg.cs">
</Event><Event ErrorLevel="0" Project="SemtechLib.Devices.SX1231" Source="SemtechLib.Devices.SX1231\Events\ExitConditionEventArg.cs" Description="File successfully backed up as C:\Users\Coskun ERGAN\Desktop\FTDI_SPI\SX1231-master\Backup\SemtechLib.Devices.SX1231\Events\ExitConditionEventArg.cs">
</Event><Event ErrorLevel="0" Project="SemtechLib.Devices.SX1231" Source="SemtechLib.Devices.SX1231\Enumerations\LimitCheckStatusEnum.cs" Description="File successfully backed up as C:\Users\Coskun ERGAN\Desktop\FTDI_SPI\SX1231-master\Backup\SemtechLib.Devices.SX1231\Enumerations\LimitCheckStatusEnum.cs">
</Event><Event ErrorLevel="0" Project="SemtechLib.Devices.SX1231" Source="SemtechLib.Devices.SX1231\Enumerations\PacketFormatEnum.cs" Description="File successfully backed up as C:\Users\Coskun ERGAN\Desktop\FTDI_SPI\SX1231-master\Backup\SemtechLib.Devices.SX1231\Enumerations\PacketFormatEnum.cs">
</Event><Event ErrorLevel="0" Project="SemtechLib.Devices.SX1231" Source="SemtechLib.Devices.SX1231\Events\RfPaSwitchSelEventHandler.cs" Description="File successfully backed up as C:\Users\Coskun ERGAN\Desktop\FTDI_SPI\SX1231-master\Backup\SemtechLib.Devices.SX1231\Events\RfPaSwitchSelEventHandler.cs">
</Event><Event ErrorLevel="0" Project="SemtechLib.Devices.SX1231" Source="SemtechLib.Devices.SX1231\Events\PaModeEventArg.cs" Description="File successfully backed up as C:\Users\Coskun ERGAN\Desktop\FTDI_SPI\SX1231-master\Backup\SemtechLib.Devices.SX1231\Events\PaModeEventArg.cs">
</Event><Event ErrorLevel="0" Project="SemtechLib.Devices.SX1231" Source="SemtechLib.Devices.SX1231\Events\PaRampEventArg.cs" Description="File successfully backed up as C:\Users\Coskun ERGAN\Desktop\FTDI_SPI\SX1231-master\Backup\SemtechLib.Devices.SX1231\Events\PaRampEventArg.cs">
</Event><Event ErrorLevel="0" Project="SemtechLib.Devices.SX1231" Source="SemtechLib.Devices.SX1231\Enumerations\ListenResolEnum.cs" Description="File successfully backed up as C:\Users\Coskun ERGAN\Desktop\FTDI_SPI\SX1231-master\Backup\SemtechLib.Devices.SX1231\Enumerations\ListenResolEnum.cs">
</Event><Event ErrorLevel="0" Project="SemtechLib.Devices.SX1231" Source="SemtechLib.Devices.SX1231\Enumerations\FifoFillConditionEnum.cs" Description="File successfully backed up as C:\Users\Coskun ERGAN\Desktop\FTDI_SPI\SX1231-master\Backup\SemtechLib.Devices.SX1231\Enumerations\FifoFillConditionEnum.cs">
</Event><Event ErrorLevel="0" Project="SemtechLib.Devices.SX1231" Source="SemtechLib.Devices.SX1231\Events\PaModeEventHandler.cs" Description="File successfully backed up as C:\Users\Coskun ERGAN\Desktop\FTDI_SPI\SX1231-master\Backup\SemtechLib.Devices.SX1231\Events\PaModeEventHandler.cs">
</Event><Event ErrorLevel="0" Project="SemtechLib.Devices.SX1231" Source="SemtechLib.Devices.SX1231\General\PacketLog.cs" Description="File successfully backed up as C:\Users\Coskun ERGAN\Desktop\FTDI_SPI\SX1231-master\Backup\SemtechLib.Devices.SX1231\General\PacketLog.cs">
</Event><Event ErrorLevel="0" Project="SemtechLib.Devices.SX1231" Source="SemtechLib.Devices.SX1231\Events\LowBatTrimEventArg.cs" Description="File successfully backed up as C:\Users\Coskun ERGAN\Desktop\FTDI_SPI\SX1231-master\Backup\SemtechLib.Devices.SX1231\Events\LowBatTrimEventArg.cs">
</Event><Event ErrorLevel="0" Project="SemtechLib.Devices.SX1231" Source="SemtechLib.Devices.SX1231\Controls\ReceiverViewControl.cs" Description="File successfully backed up as C:\Users\Coskun ERGAN\Desktop\FTDI_SPI\SX1231-master\Backup\SemtechLib.Devices.SX1231\Controls\ReceiverViewControl.cs">
</Event><Event ErrorLevel="0" Project="SemtechLib.Devices.SX1231" Source="SemtechLib.Devices.SX1231\Events\IntermediateModeEventHandler.cs" Description="File successfully backed up as C:\Users\Coskun ERGAN\Desktop\FTDI_SPI\SX1231-master\Backup\SemtechLib.Devices.SX1231\Events\IntermediateModeEventHandler.cs">
</Event><Event ErrorLevel="0" Project="SemtechLib.Devices.SX1231" Source="SemtechLib.Devices.SX1231\Events\ExitConditionEventHandler.cs" Description="File successfully backed up as C:\Users\Coskun ERGAN\Desktop\FTDI_SPI\SX1231-master\Backup\SemtechLib.Devices.SX1231\Events\ExitConditionEventHandler.cs">
</Event><Event ErrorLevel="0" Project="SemtechLib.Devices.SX1231" Source="SemtechLib.Devices.SX1231\Events\DioMappingEventHandler.cs" Description="File successfully backed up as C:\Users\Coskun ERGAN\Desktop\FTDI_SPI\SX1231-master\Backup\SemtechLib.Devices.SX1231\Events\DioMappingEventHandler.cs">
</Event><Event ErrorLevel="0" Project="SemtechLib.Devices.SX1231" Source="SemtechLib.Devices.SX1231\Events\DataModeEventArg.cs" Description="File successfully backed up as C:\Users\Coskun ERGAN\Desktop\FTDI_SPI\SX1231-master\Backup\SemtechLib.Devices.SX1231\Events\DataModeEventArg.cs">
</Event><Event ErrorLevel="0" Project="SemtechLib.Devices.SX1231" Source="SemtechLib.Devices.SX1231\Events\DioMappingEventArg.cs" Description="File successfully backed up as C:\Users\Coskun ERGAN\Desktop\FTDI_SPI\SX1231-master\Backup\SemtechLib.Devices.SX1231\Events\DioMappingEventArg.cs">
</Event><Event ErrorLevel="0" Project="SemtechLib.Devices.SX1231" Source="SemtechLib.Devices.SX1231\Enumerations\OokAverageThreshFiltEnum.cs" Description="File successfully backed up as C:\Users\Coskun ERGAN\Desktop\FTDI_SPI\SX1231-master\Backup\SemtechLib.Devices.SX1231\Enumerations\OokAverageThreshFiltEnum.cs">
</Event><Event ErrorLevel="0" Project="SemtechLib.Devices.SX1231" Source="SemtechLib.Devices.SX1231\Enumerations\ExitConditionEnum.cs" Description="File successfully backed up as C:\Users\Coskun ERGAN\Desktop\FTDI_SPI\SX1231-master\Backup\SemtechLib.Devices.SX1231\Enumerations\ExitConditionEnum.cs">
</Event><Event ErrorLevel="0" Project="SemtechLib.Devices.SX1231" Source="SemtechLib.Devices.SX1231\Events\RfPaSwitchSelEventArg.cs" Description="File successfully backed up as C:\Users\Coskun ERGAN\Desktop\FTDI_SPI\SX1231-master\Backup\SemtechLib.Devices.SX1231\Events\RfPaSwitchSelEventArg.cs">
</Event><Event ErrorLevel="0" Project="SemtechLib.Devices.SX1231" Source="SemtechLib.Devices.SX1231\Enumerations\RfPaSwitchSelEnum.cs" Description="File successfully backed up as C:\Users\Coskun ERGAN\Desktop\FTDI_SPI\SX1231-master\Backup\SemtechLib.Devices.SX1231\Enumerations\RfPaSwitchSelEnum.cs">
</Event><Event ErrorLevel="0" Project="SemtechLib.Devices.SX1231" Source="SemtechLib.Devices.SX1231\General\MaskValidationType.cs" Description="File successfully backed up as C:\Users\Coskun ERGAN\Desktop\FTDI_SPI\SX1231-master\Backup\SemtechLib.Devices.SX1231\General\MaskValidationType.cs">
</Event><Event ErrorLevel="0" Project="SemtechLib.Devices.SX1231" Source="SemtechLib.Devices.SX1231\Events\PacketFormatEventArg.cs" Description="File successfully backed up as C:\Users\Coskun ERGAN\Desktop\FTDI_SPI\SX1231-master\Backup\SemtechLib.Devices.SX1231\Events\PacketFormatEventArg.cs">
</Event><Event ErrorLevel="0" Project="SemtechLib.Devices.SX1231" Source="SemtechLib.Devices.SX1231\Events\LnaZinEventArg.cs" Description="File successfully backed up as C:\Users\Coskun ERGAN\Desktop\FTDI_SPI\SX1231-master\Backup\SemtechLib.Devices.SX1231\Events\LnaZinEventArg.cs">
</Event><Event ErrorLevel="0" Project="SemtechLib.Devices.SX1231" Source="SemtechLib.Devices.SX1231\Events\IntermediateModeEventArg.cs" Description="File successfully backed up as C:\Users\Coskun ERGAN\Desktop\FTDI_SPI\SX1231-master\Backup\SemtechLib.Devices.SX1231\Events\IntermediateModeEventArg.cs">
</Event><Event ErrorLevel="0" Project="SemtechLib.Devices.SX1231" Source="SemtechLib.Devices.SX1231\Events\ClockOutEventArg.cs" Description="File successfully backed up as C:\Users\Coskun ERGAN\Desktop\FTDI_SPI\SX1231-master\Backup\SemtechLib.Devices.SX1231\Events\ClockOutEventArg.cs">
</Event><Event ErrorLevel="0" Project="SemtechLib.Devices.SX1231" Source="SemtechLib.Devices.SX1231\Enumerations\EnterConditionEnum.cs" Description="File successfully backed up as C:\Users\Coskun ERGAN\Desktop\FTDI_SPI\SX1231-master\Backup\SemtechLib.Devices.SX1231\Enumerations\EnterConditionEnum.cs">
</Event><Event ErrorLevel="0" Project="SemtechLib.Devices.SX1231" Source="SemtechLib.Devices.SX1231\Controls\PayloadImg.cs" Description="File successfully backed up as C:\Users\Coskun ERGAN\Desktop\FTDI_SPI\SX1231-master\Backup\SemtechLib.Devices.SX1231\Controls\PayloadImg.cs">
</Event><Event ErrorLevel="0" Project="SemtechLib.Devices.SX1231" Source="SemtechLib.Devices.SX1231\Enumerations\PaRampEnum.cs" Description="File successfully backed up as C:\Users\Coskun ERGAN\Desktop\FTDI_SPI\SX1231-master\Backup\SemtechLib.Devices.SX1231\Enumerations\PaRampEnum.cs">
</Event><Event ErrorLevel="0" Project="SemtechLib.Devices.SX1231" Source="SemtechLib.Devices.SX1231\Enumerations\ClockOutEnum.cs" Description="File successfully backed up as C:\Users\Coskun ERGAN\Desktop\FTDI_SPI\SX1231-master\Backup\SemtechLib.Devices.SX1231\Enumerations\ClockOutEnum.cs">
</Event><Event ErrorLevel="0" Project="SemtechLib.Devices.SX1231" Source="SemtechLib.Devices.SX1231\Events\OokPeakThreshDecEventHandler.cs" Description="File successfully backed up as C:\Users\Coskun ERGAN\Desktop\FTDI_SPI\SX1231-master\Backup\SemtechLib.Devices.SX1231\Events\OokPeakThreshDecEventHandler.cs">
</Event><Event ErrorLevel="0" Project="SemtechLib.Devices.SX1231" Source="SemtechLib.Devices.SX1231\Events\ListenCriteriaEventHandler.cs" Description="File successfully backed up as C:\Users\Coskun ERGAN\Desktop\FTDI_SPI\SX1231-master\Backup\SemtechLib.Devices.SX1231\Events\ListenCriteriaEventHandler.cs">
</Event><Event ErrorLevel="0" Project="SemtechLib.Devices.SX1231" Source="SemtechLib.Devices.SX1231\Events\ClockOutEventHandler.cs" Description="File successfully backed up as C:\Users\Coskun ERGAN\Desktop\FTDI_SPI\SX1231-master\Backup\SemtechLib.Devices.SX1231\Events\ClockOutEventHandler.cs">
</Event><Event ErrorLevel="0" Project="SemtechLib.Devices.SX1231" Source="SemtechLib.Devices.SX1231\Events\AgcStepEventHandler.cs" Description="File successfully backed up as C:\Users\Coskun ERGAN\Desktop\FTDI_SPI\SX1231-master\Backup\SemtechLib.Devices.SX1231\Events\AgcStepEventHandler.cs">
</Event><Event ErrorLevel="0" Project="SemtechLib.Devices.SX1231" Source="SemtechLib.Devices.SX1231\General\Packet.cs" Description="File successfully backed up as C:\Users\Coskun ERGAN\Desktop\FTDI_SPI\SX1231-master\Backup\SemtechLib.Devices.SX1231\General\Packet.cs">
</Event><Event ErrorLevel="0" Project="SemtechLib.Devices.SX1231" Source="SemtechLib.Devices.SX1231\Events\ModulationTypeEventArg.cs" Description="File successfully backed up as C:\Users\Coskun ERGAN\Desktop\FTDI_SPI\SX1231-master\Backup\SemtechLib.Devices.SX1231\Events\ModulationTypeEventArg.cs">
</Event><Event ErrorLevel="0" Project="SemtechLib.Devices.SX1231" Source="SemtechLib.Devices.SX1231\Events\ListenCriteriaEventArg.cs" Description="File successfully backed up as C:\Users\Coskun ERGAN\Desktop\FTDI_SPI\SX1231-master\Backup\SemtechLib.Devices.SX1231\Events\ListenCriteriaEventArg.cs">
</Event><Event ErrorLevel="0" Project="SemtechLib.Devices.SX1231" Source="SemtechLib.Devices.SX1231\Events\OokThreshTypeEventArg.cs" Description="File successfully backed up as C:\Users\Coskun ERGAN\Desktop\FTDI_SPI\SX1231-master\Backup\SemtechLib.Devices.SX1231\Events\OokThreshTypeEventArg.cs">
</Event><Event ErrorLevel="0" Project="SemtechLib.Devices.SX1231" Source="SemtechLib.Devices.SX1231\Events\OokAverageThreshFiltEventHandler.cs" Description="File successfully backed up as C:\Users\Coskun ERGAN\Desktop\FTDI_SPI\SX1231-master\Backup\SemtechLib.Devices.SX1231\Events\OokAverageThreshFiltEventHandler.cs">
</Event><Event ErrorLevel="0" Project="SemtechLib.Devices.SX1231" Source="SemtechLib.Devices.SX1231\Events\ModulationTypeEventHandler.cs" Description="File successfully backed up as C:\Users\Coskun ERGAN\Desktop\FTDI_SPI\SX1231-master\Backup\SemtechLib.Devices.SX1231\Events\ModulationTypeEventHandler.cs">
</Event><Event ErrorLevel="0" Project="SemtechLib.Devices.SX1231" Source="SemtechLib.Devices.SX1231\Events\LnaGainEventHandler.cs" Description="File successfully backed up as C:\Users\Coskun ERGAN\Desktop\FTDI_SPI\SX1231-master\Backup\SemtechLib.Devices.SX1231\Events\LnaGainEventHandler.cs">
</Event><Event ErrorLevel="0" Project="SemtechLib.Devices.SX1231" Source="SemtechLib.Devices.SX1231\General\DataLog.cs" Description="File successfully backed up as C:\Users\Coskun ERGAN\Desktop\FTDI_SPI\SX1231-master\Backup\SemtechLib.Devices.SX1231\General\DataLog.cs">
</Event><Event ErrorLevel="0" Project="SemtechLib.Devices.SX1231" Source="SemtechLib.Devices.SX1231\Events\ListenEndEventArg.cs" Description="File successfully backed up as C:\Users\Coskun ERGAN\Desktop\FTDI_SPI\SX1231-master\Backup\SemtechLib.Devices.SX1231\Events\ListenEndEventArg.cs">
</Event><Event ErrorLevel="0" Project="SemtechLib.Devices.SX1231" Source="SemtechLib.Devices.SX1231\Enumerations\OokPeakThreshDecEnum.cs" Description="File successfully backed up as C:\Users\Coskun ERGAN\Desktop\FTDI_SPI\SX1231-master\Backup\SemtechLib.Devices.SX1231\Enumerations\OokPeakThreshDecEnum.cs">
</Event><Event ErrorLevel="0" Project="SemtechLib.Devices.SX1231" Source="SemtechLib.Devices.SX1231\Enumerations\DcFreeEnum.cs" Description="File successfully backed up as C:\Users\Coskun ERGAN\Desktop\FTDI_SPI\SX1231-master\Backup\SemtechLib.Devices.SX1231\Enumerations\DcFreeEnum.cs">
</Event><Event ErrorLevel="0" Project="SemtechLib.Devices.SX1231" Source="SemtechLib.Devices.SX1231\Enumerations\AddressFilteringEnum.cs" Description="File successfully backed up as C:\Users\Coskun ERGAN\Desktop\FTDI_SPI\SX1231-master\Backup\SemtechLib.Devices.SX1231\Enumerations\AddressFilteringEnum.cs">
</Event><Event ErrorLevel="0" Project="SemtechLib.Devices.SX1231" Source="SemtechLib.Devices.SX1231\Events\DataModeEventHandler.cs" Description="File successfully backed up as C:\Users\Coskun ERGAN\Desktop\FTDI_SPI\SX1231-master\Backup\SemtechLib.Devices.SX1231\Events\DataModeEventHandler.cs">
</Event><Event ErrorLevel="0" Project="SemtechLib.Devices.SX1231" Source="SemtechLib.Devices.SX1231\Events\ListenResolEventArg.cs" Description="File successfully backed up as C:\Users\Coskun ERGAN\Desktop\FTDI_SPI\SX1231-master\Backup\SemtechLib.Devices.SX1231\Events\ListenResolEventArg.cs">
</Event><Event ErrorLevel="0" Project="SemtechLib.Devices.SX1231" Source="SemtechLib.Devices.SX1231\Events\PacketStatusEventArg.cs" Description="File successfully backed up as C:\Users\Coskun ERGAN\Desktop\FTDI_SPI\SX1231-master\Backup\SemtechLib.Devices.SX1231\Events\PacketStatusEventArg.cs">
</Event><Event ErrorLevel="0" Project="SemtechLib.Devices.SX1231" Source="SemtechLib.Devices.SX1231\Events\AddressFilteringEventArg.cs" Description="File successfully backed up as C:\Users\Coskun ERGAN\Desktop\FTDI_SPI\SX1231-master\Backup\SemtechLib.Devices.SX1231\Events\AddressFilteringEventArg.cs">
</Event><Event ErrorLevel="0" Project="SemtechLib.Devices.SX1231" Source="SemtechLib.Devices.SX1231\Events\PacketFormatEventHandler.cs" Description="File successfully backed up as C:\Users\Coskun ERGAN\Desktop\FTDI_SPI\SX1231-master\Backup\SemtechLib.Devices.SX1231\Events\PacketFormatEventHandler.cs">
</Event><Event ErrorLevel="0" Project="SemtechLib.Devices.SX1231" Source="SemtechLib.Devices.SX1231\Events\LowBatTrimEventHandler.cs" Description="File successfully backed up as C:\Users\Coskun ERGAN\Desktop\FTDI_SPI\SX1231-master\Backup\SemtechLib.Devices.SX1231\Events\LowBatTrimEventHandler.cs">
</Event><Event ErrorLevel="0" Project="SemtechLib.Devices.SX1231" Source="SemtechLib.Devices.SX1231\Events\ListenResolEventHandler.cs" Description="File successfully backed up as C:\Users\Coskun ERGAN\Desktop\FTDI_SPI\SX1231-master\Backup\SemtechLib.Devices.SX1231\Events\ListenResolEventHandler.cs">
</Event><Event ErrorLevel="0" Project="SemtechLib.Devices.SX1231" Source="SemtechLib.Devices.SX1231\Controls\CommonViewControl.resx" Description="File successfully backed up as C:\Users\Coskun ERGAN\Desktop\FTDI_SPI\SX1231-master\Backup\SemtechLib.Devices.SX1231\Controls\CommonViewControl.resx">
</Event><Event ErrorLevel="0" Project="SemtechLib.Devices.SX1231" Source="SemtechLib.Devices.SX1231\Controls\DeviceViewControl.resx" Description="File successfully backed up as C:\Users\Coskun ERGAN\Desktop\FTDI_SPI\SX1231-master\Backup\SemtechLib.Devices.SX1231\Controls\DeviceViewControl.resx">
</Event><Event ErrorLevel="0" Project="SemtechLib.Devices.SX1231" Source="SemtechLib.Devices.SX1231\Controls\IrqMapViewControl.resx" Description="File successfully backed up as C:\Users\Coskun ERGAN\Desktop\FTDI_SPI\SX1231-master\Backup\SemtechLib.Devices.SX1231\Controls\IrqMapViewControl.resx">
</Event><Event ErrorLevel="0" Project="SemtechLib.Devices.SX1231" Source="SemtechLib.Devices.SX1231\Controls\PacketHandlerView.resx" Description="File successfully backed up as C:\Users\Coskun ERGAN\Desktop\FTDI_SPI\SX1231-master\Backup\SemtechLib.Devices.SX1231\Controls\PacketHandlerView.resx">
</Event><Event ErrorLevel="0" Project="SemtechLib.Devices.SX1231" Source="SemtechLib.Devices.SX1231\Controls\ReceiverViewControl.resx" Description="File successfully backed up as C:\Users\Coskun ERGAN\Desktop\FTDI_SPI\SX1231-master\Backup\SemtechLib.Devices.SX1231\Controls\ReceiverViewControl.resx">
</Event><Event ErrorLevel="0" Project="SemtechLib.Devices.SX1231" Source="SemtechLib.Devices.SX1231\Controls\RegisterTableControl.resx" Description="File successfully backed up as C:\Users\Coskun ERGAN\Desktop\FTDI_SPI\SX1231-master\Backup\SemtechLib.Devices.SX1231\Controls\RegisterTableControl.resx">
</Event><Event ErrorLevel="0" Project="SemtechLib.Devices.SX1231" Source="SemtechLib.Devices.SX1231\Controls\RssiGraphControl.resx" Description="File successfully backed up as C:\Users\Coskun ERGAN\Desktop\FTDI_SPI\SX1231-master\Backup\SemtechLib.Devices.SX1231\Controls\RssiGraphControl.resx">
</Event><Event ErrorLevel="0" Project="SemtechLib.Devices.SX1231" Source="SemtechLib.Devices.SX1231\Controls\SpectrumGraphControl.resx" Description="File successfully backed up as C:\Users\Coskun ERGAN\Desktop\FTDI_SPI\SX1231-master\Backup\SemtechLib.Devices.SX1231\Controls\SpectrumGraphControl.resx">
</Event><Event ErrorLevel="0" Project="SemtechLib.Devices.SX1231" Source="SemtechLib.Devices.SX1231\Controls\TemperatureViewControl.resx" Description="File successfully backed up as C:\Users\Coskun ERGAN\Desktop\FTDI_SPI\SX1231-master\Backup\SemtechLib.Devices.SX1231\Controls\TemperatureViewControl.resx">
</Event><Event ErrorLevel="0" Project="SemtechLib.Devices.SX1231" Source="SemtechLib.Devices.SX1231\Controls\TransmitterViewControl.resx" Description="File successfully backed up as C:\Users\Coskun ERGAN\Desktop\FTDI_SPI\SX1231-master\Backup\SemtechLib.Devices.SX1231\Controls\TransmitterViewControl.resx">
</Event><Event ErrorLevel="0" Project="SemtechLib.Devices.SX1231" Source="SemtechLib.Devices.SX1231\Forms\PacketLogForm.resx" Description="File successfully backed up as C:\Users\Coskun ERGAN\Desktop\FTDI_SPI\SX1231-master\Backup\SemtechLib.Devices.SX1231\Forms\PacketLogForm.resx">
</Event><Event ErrorLevel="0" Project="SemtechLib.Devices.SX1231" Source="SemtechLib.Devices.SX1231\Forms\RegistersForm.resx" Description="File successfully backed up as C:\Users\Coskun ERGAN\Desktop\FTDI_SPI\SX1231-master\Backup\SemtechLib.Devices.SX1231\Forms\RegistersForm.resx">
</Event><Event ErrorLevel="0" Project="SemtechLib.Devices.SX1231" Source="SemtechLib.Devices.SX1231\Forms\RssiAnalyserForm.resx" Description="File successfully backed up as C:\Users\Coskun ERGAN\Desktop\FTDI_SPI\SX1231-master\Backup\SemtechLib.Devices.SX1231\Forms\RssiAnalyserForm.resx">
</Event><Event ErrorLevel="0" Project="SemtechLib.Devices.SX1231" Source="SemtechLib.Devices.SX1231\Forms\SpectrumAnalyserForm.resx" Description="File successfully backed up as C:\Users\Coskun ERGAN\Desktop\FTDI_SPI\SX1231-master\Backup\SemtechLib.Devices.SX1231\Forms\SpectrumAnalyserForm.resx">
</Event><Event ErrorLevel="0" Project="SemtechLib.Devices.SX1231" Source="SemtechLib.Devices.SX1231\Forms\TemperatureCalibrationForm.resx" Description="File successfully backed up as C:\Users\Coskun ERGAN\Desktop\FTDI_SPI\SX1231-master\Backup\SemtechLib.Devices.SX1231\Forms\TemperatureCalibrationForm.resx">
</Event><Event ErrorLevel="0" Project="SemtechLib.Devices.SX1231" Source="SemtechLib.Devices.SX1231\Forms\TestForm.resx" Description="File successfully backed up as C:\Users\Coskun ERGAN\Desktop\FTDI_SPI\SX1231-master\Backup\SemtechLib.Devices.SX1231\Forms\TestForm.resx">
</Event><Event ErrorLevel="0" Project="SemtechLib.Devices.SX1231" Source="SemtechLib.Devices.SX1231\Properties\Resources.resx" Description="File successfully backed up as C:\Users\Coskun ERGAN\Desktop\FTDI_SPI\SX1231-master\Backup\SemtechLib.Devices.SX1231\Properties\Resources.resx">
</Event><Event ErrorLevel="0" Project="SemtechLib.Devices.SX1231" Source="SemtechLib.Devices.SX1231\SemtechLib.Devices.SX1231.csproj" Description="The project file does not require conversion.">
</Event><Event ErrorLevel="3" Project="SemtechLib.Devices.SX1231" Source="SemtechLib.Devices.SX1231\SemtechLib.Devices.SX1231.csproj" Description="No Conversion Required">
</Event><Event ErrorLevel="0" Project="FTD2XX_NET" Source="FTD2XX_NET\FTD2XX_NET.csproj" Description="Project file successfully backed up as C:\Users\Coskun ERGAN\Desktop\FTDI_SPI\SX1231-master\Backup\FTD2XX_NET\FTD2XX_NET.csproj">
</Event><Event ErrorLevel="0" Project="FTD2XX_NET" Source="FTD2XX_NET\FTDI.cs" Description="File successfully backed up as C:\Users\Coskun ERGAN\Desktop\FTDI_SPI\SX1231-master\Backup\FTD2XX_NET\FTDI.cs">
</Event><Event ErrorLevel="0" Project="FTD2XX_NET" Source="FTD2XX_NET\Properties\Resources.cs" Description="File successfully backed up as C:\Users\Coskun ERGAN\Desktop\FTDI_SPI\SX1231-master\Backup\FTD2XX_NET\Properties\Resources.cs">
</Event><Event ErrorLevel="0" Project="FTD2XX_NET" Source="FTD2XX_NET\AssemblyInfo.cs" Description="File successfully backed up as C:\Users\Coskun ERGAN\Desktop\FTDI_SPI\SX1231-master\Backup\FTD2XX_NET\AssemblyInfo.cs">
</Event><Event ErrorLevel="0" Project="FTD2XX_NET" Source="FTD2XX_NET\ftd2xx.dll" Description="File successfully backed up as C:\Users\Coskun ERGAN\Desktop\FTDI_SPI\SX1231-master\Backup\FTD2XX_NET\ftd2xx.dll">
</Event><Event ErrorLevel="0" Project="FTD2XX_NET" Source="FTD2XX_NET\ftd2xx64.dll" Description="File successfully backed up as C:\Users\Coskun ERGAN\Desktop\FTDI_SPI\SX1231-master\Backup\FTD2XX_NET\ftd2xx64.dll">
</Event><Event ErrorLevel="0" Project="FTD2XX_NET" Source="FTD2XX_NET\Properties\Resources.resx" Description="File successfully backed up as C:\Users\Coskun ERGAN\Desktop\FTDI_SPI\SX1231-master\Backup\FTD2XX_NET\Properties\Resources.resx">
</Event><Event ErrorLevel="0" Project="FTD2XX_NET" Source="FTD2XX_NET\FTD2XX_NET.csproj" Description="Project converted successfully">
</Event><Event ErrorLevel="3" Project="FTD2XX_NET" Source="FTD2XX_NET\FTD2XX_NET.csproj" Description="Converted">
</Event><Event ErrorLevel="0" Project="" Source="sx1231skb.sln" Description="The solution file does not require conversion.">
</Event><Event ErrorLevel="3" Project="" Source="sx1231skb.sln" Description="No Conversion Required">
</Event><Event ErrorLevel="0" Project="FTD2XX_NET" Source="FTD2XX_NET\FTD2XX_NET.csproj" Description="Scan complete: Upgrade not required for project files.">
</Event></UpgradeLog>